dm.v
module dm(
input clk,
input wire[31:0] result,
input wire[31:0] WriteData,
input wire zero, 
input wire MemWrite, 
input wire MemRead,
output reg[31:0] ReadData);

//1024 words of 32-bit memory
reg[31:0] mem[0:1023]; 
integer i;

initial begin		
//assign values to memory bits, in ascendant order, from 0 to 1023
	for (i=0; i<1023; i=i+1)
		mem[i] = i;
end

always @(posedge clk) begin
	if (MemWrite == 1) begin		//sw
		mem[result]= WriteData;		//write value of WriteData into mem[result]
	end
	if (MemRead == 1) begin			//lw
		ReadData = mem[result]; 	//write value of mem[result] into reg ReadData - the output
	end
end

endmodule

dm_tb.v
`include "dm.v"

module dm_tb;

reg clk;
reg[31:0] result;
reg[31:0] WriteData;
reg zero; 
reg MemWrite; 
reg MemRead;
wire[31:0] ReadData;

dm trial (.clk(clk), .result(result), .WriteData(WriteData), .zero(zero), .MemWrite(MemWrite), .MemRead(MemRead), .ReadData(ReadData));

initial clk = 0;

initial begin
	$dumpfile("dm.vcd");	
	$dumpvars(0, dm_tb);
	
	result = 4'b0000;
	WriteData = 0;
	zero = 0;
	MemWrite = 0;
	MemRead = 0;
	#10;
	
	result = 4'b0001;
	WriteData = 0;
	zero = 0;
	MemWrite = 0;
	MemRead = 1;
	#10;
	
	result = 4'b0010;
	WriteData = 0;
	zero = 0;
	MemWrite = 1;
	MemRead = 0;
	#10;

	result = 4'b0011;
	WriteData = 0;
	zero = 0;
	MemWrite = 1;
	MemRead = 1;
	#10;

	result = 4'b0100;
	WriteData = 1;
	zero = 0;
	MemWrite = 0;
	MemRead = 0;
	#10;

	result = 4'b0101;
	WriteData =1;
	zero = 0;
	MemWrite = 0;
	MemRead = 1;
	#10;

	result = 4'b0110;
	WriteData = 1;
	zero = 0;
	MemWrite = 1;
	MemRead = 0;
	#10;
	
	result = 4'b0111;
	WriteData = 1;
	zero = 0;
	MemWrite = 1;
	MemRead = 1;
	#10;
end

always 
 #5 clk = !clk;

initial 
 #100 $finish;
endmodule

dm.vcd
$date
	Tue Oct  9 23:54:26 2018
$end
$version
	Icarus Verilog
$end
$timescale
	1s
$end
$scope module dm_tb $end
$var wire 32 ! ReadData [31:0] $end
$var reg 1 " MemRead $end
$var reg 1 # MemWrite $end
$var reg 32 $ WriteData [31:0] $end
$var reg 1 % clk $end
$var reg 32 & result [31:0] $end
$var reg 1 ' zero $end
$scope module trial $end
$var wire 1 " MemRead $end
$var wire 1 # MemWrite $end
$var wire 32 ( WriteData [31:0] $end
$var wire 1 % clk $end
$var wire 32 ) result [31:0] $end
$var wire 1 ' zero $end
$var reg 32 * ReadData [31:0] $end
$var integer 32 + i [31:0] $end
$upscope $end
$upscope $end
$enddefinitions $end
#0
$dumpvars
b10000000000 +
bx *
b0 )
b0 (
0'
b0 &
0%
b0 $
0#
0"
bx !
$end
#5
1%
#10
0%
1"
b1 &
b1 )
#15
b1 !
b1 *
1%
#20
0%
0"
1#
b10 &
b10 )
#25
1%
#30
0%
1"
b11 &
b11 )
#35
b0 !
b0 *
1%
#40
0%
0"
0#
b1 $
b1 (
b100 &
b100 )
#45
1%
#50
0%
1"
b101 &
b101 )
#55
b101 !
b101 *
1%
#60
0%
0"
1#
b110 &
b110 )
#65
1%
#70
0%
1"
b111 &
b111 )
#75
b1 !
b1 *
1%
