im.v
module im(clk, address, instr);

input clk;
input wire[31:0] address;
output reg[31:0][31:0] instr;		//2d array of type [address][location]
	
reg [31:0] location; 

initial begin
	if (address == 4'b0000) location = 4'b0001;	//hardcoded values of location
	else if (address == 4'b0001) location = 4'b0010;
	else if (address == 4'b0010) location = 4'b0011;
end

always @(posedge clk)
begin	
	if (address ==4'b0000)	begin		//temp[32'h0000][32'h0001] = 32'h0010;
		instr = 4'b0010;
	end
	else if (address == 4'b0001) begin	//temp[32'h0001][32'h0010] = 32'h0011;
		instr = 4'b0011;
	end
	if (address == 4'b0010)begin		//temp[32'h0010][32'h0011] = 32'h0100;
		instr =4'b0100;
	end	
end

endmodule

im_tb.v
`include "im.v"

module im_tb;

reg clk;
reg [31:0] address;
wire [31:0][31:0] instr;

im trial(.clk(clk), .address(address), .instr(instr));


initial begin
	$dumpfile("im.vcd");	
	$dumpvars(0, im_tb);
end 


initial begin
	clk = 0;
	address = 4'b0000; 	
	#30;
	
	address = 4'b0001;
	#30;

	address =4'b0010;
	#30;

	address = 4'b0011;
	#30;

	address = 4'b0100;
	#30;
		
end

always 
#5 clk = !clk;

initial 
 #200 $finish;

endmodule

im.vcd
$date
	Wed Oct 10 00:01:55 2018
$end
$version
	Icarus Verilog
$end
$timescale
	1s
$end
$scope module im_tb $end
$var wire 1024 ! instr [1023:0] $end
$var reg 32 " address [31:0] $end
$var reg 1 # clk $end
$scope module trial $end
$var wire 32 $ address [31:0] $end
$var wire 1 # clk $end
$var reg 1024 % instr [1023:0] $end
$var reg 32 & location [31:0] $end
$upscope $end
$upscope $end
$enddefinitions $end
#0
$dumpvars
bx &
bx %
b0 $
0#
b0 "
bx !
$end
#5
b10 !
b10 %
1#
#10
0#
#15
1#
#20
0#
#25
1#
#30
0#
b1 "
b1 $
#35
b11 !
b11 %
1#
#40
0#
#45
1#
#50
0#
#55
1#
#60
0#
b10 "
b10 $
#65
b100 !
b100 %
1#
#70
0#
#75
1#
#80
0#
#85
1#
#90
0#
b11 "
b11 $
#95
1#
#100
0#
#105
1#
#110
0#
#115
1#
#120
0#
b100 "
b100 $
