reg.v
module registers
(input clk, 
input wire[4:0] reg1, 		//read register 1
input wire[4:0] reg2, 		//read register 2
input wire[4:0] writeReg,		//write register
input wire[31:0] WriteData,   	//input from Data Memory
input wire RegWrite,		//signal
output reg[31:0] read1,
output reg[31:0] read2); 

reg[31:0] Registers[31:0]; //array of 32 registers, 32-bit each

initial begin
	Registers[0] <= 32'h00000;	//hardcoded values of the registers
	Registers[1] <= 32'h00001;
	Registers[2] <= 32'h00010;
	Registers[3] <= 32'h00011;
	Registers[4] <= 32'h00100;
	Registers[5] <= 32'h00101;
	Registers[6] <= 32'h00110;
	Registers[7] <= 32'h00111;
	Registers[8] <= 32'h01000;
	Registers[9] <= 32'h01001;
	Registers[10] <= 32'h01010;
	Registers[11] <= 32'h01011;
	Registers[12] <= 32'h01100;
	Registers[13] <= 32'h01101;
	Registers[14] <= 32'h01110;
	Registers[15] <= 32'h01111;
	Registers[16] <= 32'h10000;
	Registers[17] <= 32'h10001;
	Registers[18] <= 32'h10010;
	Registers[19] <= 32'h10011;
	Registers[20] <= 32'h10100;
	Registers[21] <= 32'h10101;
	Registers[22] <= 32'h10110;
	Registers[23] <= 32'h10111;
	Registers[24] <= 32'h11000;
	Registers[25] <= 32'h11001;
	Registers[26] <= 32'h11010;
	Registers[27] <= 32'h11011;
	Registers[28] <= 32'h11100;
	Registers[29] <= 32'h11101;
	Registers[30] <= 32'h11110;
	Registers[31] <= 32'h11111;
end 

always @(posedge clk) begin
	if (RegWrite == 1)			//store word in memory
	begin
		Registers[writeReg] = WriteData; 	//store value of WriteData into Registers[rd]
	end
	
 	if (RegWrite ==0) begin			//if the instruction is different from sw, WriteData is 0
		 Registers[0] = WriteData;
	end
	
	read1 = Registers[reg1];
	read2 = Registers[reg2];
end 

endmodule

reg_tb.v
`include "reg.v"

module reg_tb;

reg clk;
reg[4:0] reg1;
reg[4:0] reg2; 
reg[4:0] writeReg;
reg[31:0] WriteData;   //input from Data Memory
reg RegWrite;
wire[31:0] read1;
wire[31:0] read2;

registers trial(.clk(clk), .reg1(reg1), .reg2(reg2), .writeReg(writeReg), .WriteData(WriteData), .RegWrite(RegWrite), .read1(read1), .read2(read2));

initial clk = 0;

initial begin
	$dumpfile("reg.vcd");	
	$dumpvars(0, reg_tb);
	
	RegWrite = 1; 	
	reg1 = 00000; 
	reg2 = 00000; 
	writeReg = 00001; 
	WriteData = 32'h11100000; 
	#20;
	
	RegWrite = 1; 	
	reg1 = 1; 
	reg2 = 2; 
	writeReg = 3; 
	WriteData = 32'h10000000; 
	#20;

	RegWrite = 1; 	
	reg1 = 2; 
	reg2 = 4; 
	writeReg = 5; 
	WriteData = 32'h00000010; 
	#20;

	RegWrite = 0;  
	reg1 = 1; 
	reg2 = 10; 
	WriteData = 32'h00000001; 
	#20;
end

always 
#5 clk = !clk;

initial 
 #100 $finish;
endmodule

reg.vcd
$date
	Wed Oct 10 00:40:57 2018
$end
$version
	Icarus Verilog
$end
$timescale
	1s
$end
$scope module reg_tb $end
$var wire 32 ! read2 [31:0] $end
$var wire 32 " read1 [31:0] $end
$var reg 1 # RegWrite $end
$var reg 32 $ WriteData [31:0] $end
$var reg 1 % clk $end
$var reg 5 & reg1 [4:0] $end
$var reg 5 ' reg2 [4:0] $end
$var reg 5 ( writeReg [4:0] $end
$scope module trial $end
$var wire 1 # RegWrite $end
$var wire 32 ) WriteData [31:0] $end
$var wire 1 % clk $end
$var wire 5 * reg1 [4:0] $end
$var wire 5 + reg2 [4:0] $end
$var wire 5 , writeReg [4:0] $end
$var reg 32 - read1 [31:0] $end
$var reg 32 . read2 [31:0] $end
$upscope $end
$upscope $end
$enddefinitions $end
#0
$dumpvars
bx .
bx -
b1 ,
b0 +
b0 *
b10001000100000000000000000000 )
b1 (
b0 '
b0 &
0%
b10001000100000000000000000000 $
1#
bx "
bx !
$end
#5
b0 !
b0 .
b0 "
b0 -
1%
#10
0%
#15
1%
#20
0%
b10000000000000000000000000000 $
b10000000000000000000000000000 )
b11 (
b11 ,
b10 '
b10 +
b1 &
b1 *
#25
b10000 !
b10000 .
b10001000100000000000000000000 "
b10001000100000000000000000000 -
1%
#30
0%
#35
1%
#40
0%
b10000 $
b10000 )
b101 (
b101 ,
b100 '
b100 +
b10 &
b10 *
#45
b100000000 !
b100000000 .
b10000 "
b10000 -
1%
#50
0%
#55
1%
#60
0%
b1 $
b1 )
b1010 '
b1010 +
b1 &
b1 *
0#
#65
b1000000010000 !
b1000000010000 .
b10001000100000000000000000000 "
b10001000100000000000000000000 -
1%
